lightdock/__init__.py
lightdock/constants.py
lightdock/version.py
lightdock/error/__init__.py
lightdock/error/lightdock_errors.py
lightdock/etc/glowworm.conf
lightdock/gso/__init__.py
lightdock/gso/algorithm.py
lightdock/gso/boundaries.py
lightdock/gso/coordinates.py
lightdock/gso/glowworm.py
lightdock/gso/initializer.py
lightdock/gso/parameters.py
lightdock/gso/swarm.py
lightdock/gso/searchspace/__init__.py
lightdock/gso/searchspace/benchmark_ofunctions.py
lightdock/gso/searchspace/landscape.py
lightdock/gso/searchspace/ofunction.py
lightdock/gso/searchspace/cython/__init__.py
lightdock/gso/searchspace/cython/j1.c
lightdock/gso/searchspace/cython/j1.cpython-38-darwin.so
lightdock/gso/searchspace/cython/j2.c
lightdock/gso/searchspace/cython/j2.cpython-38-darwin.so
lightdock/gso/searchspace/cython/j3.c
lightdock/gso/searchspace/cython/j3.cpython-38-darwin.so
lightdock/gso/searchspace/cython/j4.c
lightdock/gso/searchspace/cython/j4.cpython-38-darwin.so
lightdock/gso/searchspace/cython/j5.c
lightdock/gso/searchspace/cython/j5.cpython-38-darwin.so
lightdock/gso/searchspace/cython/setup.py
lightdock/mathutil/__init__.py
lightdock/mathutil/constants.py
lightdock/mathutil/ellipsoid.py
lightdock/mathutil/lrandom.py
lightdock/mathutil/cython/__init__.py
lightdock/mathutil/cython/cutil.c
lightdock/mathutil/cython/cutil.cpython-38-darwin.so
lightdock/mathutil/cython/quaternion.c
lightdock/mathutil/cython/quaternion.cpython-38-darwin.so
lightdock/mathutil/cython/setup.py
lightdock/parallel/__init__.py
lightdock/parallel/kraken.py
lightdock/parallel/util.py
lightdock/pdbutil/PDBIO.py
lightdock/pdbutil/__init__.py
lightdock/prep/__init__.py
lightdock/prep/ftdock.py
lightdock/prep/geometry.py
lightdock/prep/poses.py
lightdock/prep/simulation.py
lightdock/prep/starting_points.py
lightdock/scoring/__init__.py
lightdock/scoring/functions.py
lightdock/scoring/multiple.py
lightdock/scoring/cpydock/__init__.py
lightdock/scoring/cpydock/driver.py
lightdock-0.8.2.dist-info/LICENSE
lightdock-0.8.2.dist-info/METADATA
lightdock-0.8.2.dist-info/WHEEL
lightdock-0.8.2.dist-info/top_level.txt
lightdock-0.8.2.dist-info/RECORD
