Metadata-Version: 2.1
Name: lightdock
Version: 0.8.2
Summary: A macromolecular docking framework
Home-page: https://lightdock.org/
License: GPLv3 License
Platform: UNKNOWN
Classifier: Development Status :: 5 - Production/Stable
Classifier: Environment :: Console
Classifier: Intended Audience :: Education
Classifier: Intended Audience :: Science/Research
Classifier: License :: OSI Approved :: GNU General Public License v3 (GPLv3)
Classifier: Programming Language :: Python :: 3
Classifier: Programming Language :: Python :: 3.6
Classifier: Programming Language :: Python :: 3.7
Classifier: Programming Language :: Python :: 3.8
Classifier: Programming Language :: Python :: 3.9
Classifier: Operating System :: MacOS :: MacOS X
Classifier: Operating System :: POSIX
Classifier: Programming Language :: Python :: Implementation :: CPython
Classifier: Topic :: Scientific/Engineering :: Artificial Intelligence
Classifier: Topic :: Scientific/Engineering :: Bio-Informatics
Classifier: Topic :: Scientific/Engineering :: Chemistry
Requires-Python: >=3.6
Requires-Dist: numpy (>=1.17.1)
Requires-Dist: scipy (<1.6,>=1.3.1)
Requires-Dist: cython (>=0.29.13)
Requires-Dist: pyparsing (==2.4.7)
Requires-Dist: prody (==1.10.11)
Requires-Dist: freesasa (>=2.0.3)
